modularizador_ipynb.py
modularizador/__init__.py
modularizador/_modularizador_ipynb.py
modularizador/modularizador_ipynb.py
modularizador-1.0.13.dist-info/LICENSE
modularizador-1.0.13.dist-info/METADATA
modularizador-1.0.13.dist-info/WHEEL
modularizador-1.0.13.dist-info/top_level.txt
modularizador-1.0.13.dist-info/RECORD
