Metadata-Version: 2.1
Name: modularizador
Version: 1.0.13
Summary: Importe arquivos .ipynb como se fossem arquivos .py no Jupyter Notebook /\/\/\ Import .ipynb files as if they were .py files on Jupyter Notebook
Home-page: 
Author: Heitor Leal Farnese
Author-email: heitor.leal.farnese@gmail.com
Keywords: módulos ipynb jupyter notebook py importar importação import importation importing modules ipython
Classifier: Programming Language :: Python :: 3
Classifier: Operating System :: OS Independent
License-File: LICENSE
